chinese_matplotlib/__init__.py
chinese_matplotlib/font_manager.py
chinese_matplotlib-0.1.2.dist-info/METADATA
chinese_matplotlib-0.1.2.dist-info/WHEEL
chinese_matplotlib-0.1.2.dist-info/top_level.txt
chinese_matplotlib-0.1.2.dist-info/RECORD
