Metadata-Version: 2.4
Name: chinese_matplotlib
Version: 0.1.2
Summary: 自动设置Matplotlib中文字体
Author: wudong
Author-email: dongw1997@gmail.com
License: MIT
Classifier: Programming Language :: Python :: 3
Classifier: License :: OSI Approved :: MIT License
Classifier: Operating System :: OS Independent
Requires-Python: >=3.6
Requires-Dist: matplotlib
